{
    "asset": {
        "format": "png",
        "id": "752d656974948854da67066b172a066f",
        "name": "train135.png",
        "path": "file:/home/pavithran/synthdata/train/train135.png",
        "size": {
            "width": 500,
            "height": 500
        },
        "state": 2,
        "type": 1,
        "predicted": true
    },
    "regions": [
        {
            "id": "1hBjTTSmV",
            "type": "RECTANGLE",
            "tags": [
                "slope"
            ],
            "boundingBox": {
                "height": 16.701936721801758,
                "width": 18.422925063541957,
                "left": 246.85714285714283,
                "top": 243.2369887828827
            },
            "points": [
                {
                    "x": 246.85714285714283,
                    "y": 243.2369887828827
                },
                {
                    "x": 265.2800679206848,
                    "y": 243.2369887828827
                },
                {
                    "x": 265.2800679206848,
                    "y": 259.93892550468445
                },
                {
                    "x": 246.85714285714283,
                    "y": 259.93892550468445
                }
            ]
        },
        {
            "id": "Gdcl8u3PH8",
            "type": "RECTANGLE",
            "tags": [
                "flat"
            ],
            "boundingBox": {
                "height": 22.40931987762451,
                "width": 22.798106602260045,
                "left": 396.0590362548828,
                "top": 461.3232910633087
            },
            "points": [
                {
                    "x": 396.0590362548828,
                    "y": 461.3232910633087
                },
                {
                    "x": 418.85714285714283,
                    "y": 461.3232910633087
                },
                {
                    "x": 418.85714285714283,
                    "y": 483.7326109409332
                },
                {
                    "x": 396.0590362548828,
                    "y": 483.7326109409332
                }
            ]
        },
        {
            "id": "fnnaipu6_b",
            "type": "RECTANGLE",
            "tags": [
                "flat"
            ],
            "boundingBox": {
                "left": 190.5275285243988,
                "top": 190.92783331871033,
                "width": 8.91721248626709,
                "height": 9.397566318511963
            },
            "points": [
                {
                    "x": 190.5275285243988,
                    "y": 190.92783331871033
                },
                {
                    "x": 199.4447410106659,
                    "y": 190.92783331871033
                },
                {
                    "x": 199.4447410106659,
                    "y": 200.3253996372223
                },
                {
                    "x": 190.5275285243988,
                    "y": 200.3253996372223
                }
            ]
        },
        {
            "id": "7pl2YIvFbH",
            "type": "RECTANGLE",
            "tags": [
                "depth"
            ],
            "boundingBox": {
                "height": 41.714285714285715,
                "width": 38.285714285714285,
                "left": 7.428571428571426,
                "top": 174.85714285714286
            },
            "points": [
                {
                    "x": 7.428571428571426,
                    "y": 174.85714285714286
                },
                {
                    "x": 45.71428571428571,
                    "y": 174.85714285714286
                },
                {
                    "x": 45.71428571428571,
                    "y": 216.57142857142856
                },
                {
                    "x": 7.428571428571426,
                    "y": 216.57142857142856
                }
            ]
        },
        {
            "id": "m7GXBgMB8T",
            "type": "RECTANGLE",
            "tags": [
                "depth"
            ],
            "boundingBox": {
                "height": 51.74807967458455,
                "width": 54.285714285714285,
                "left": 64,
                "top": 113.39477746827258
            },
            "points": [
                {
                    "x": 64,
                    "y": 113.39477746827258
                },
                {
                    "x": 118.28571428571428,
                    "y": 113.39477746827258
                },
                {
                    "x": 118.28571428571428,
                    "y": 165.14285714285714
                },
                {
                    "x": 64,
                    "y": 165.14285714285714
                }
            ]
        },
        {
            "id": "VTLqxWj9w",
            "type": "RECTANGLE",
            "tags": [
                "slope"
            ],
            "boundingBox": {
                "height": 30.857142857142854,
                "width": 32.57142857142857,
                "left": 64.28571428571428,
                "top": 180.57142857142856
            },
            "points": [
                {
                    "x": 64.28571428571428,
                    "y": 180.57142857142856
                },
                {
                    "x": 96.85714285714285,
                    "y": 180.57142857142856
                },
                {
                    "x": 96.85714285714285,
                    "y": 211.42857142857142
                },
                {
                    "x": 64.28571428571428,
                    "y": 211.42857142857142
                }
            ]
        },
        {
            "id": "TN7a9mkXI",
            "type": "RECTANGLE",
            "tags": [
                "flat"
            ],
            "boundingBox": {
                "height": 16,
                "width": 14.285714285714285,
                "left": 184.85714285714283,
                "top": 358.2857142857143
            },
            "points": [
                {
                    "x": 184.85714285714283,
                    "y": 358.2857142857143
                },
                {
                    "x": 199.14285714285714,
                    "y": 358.2857142857143
                },
                {
                    "x": 199.14285714285714,
                    "y": 374.2857142857143
                },
                {
                    "x": 184.85714285714283,
                    "y": 374.2857142857143
                }
            ]
        },
        {
            "id": "GEpN3xA1y",
            "type": "RECTANGLE",
            "tags": [
                "flat"
            ],
            "boundingBox": {
                "height": 12,
                "width": 12,
                "left": 82,
                "top": 291.4285714285714
            },
            "points": [
                {
                    "x": 82,
                    "y": 291.4285714285714
                },
                {
                    "x": 94,
                    "y": 291.4285714285714
                },
                {
                    "x": 94,
                    "y": 303.4285714285714
                },
                {
                    "x": 82,
                    "y": 303.4285714285714
                }
            ]
        },
        {
            "id": "IAV1BF8IX",
            "type": "RECTANGLE",
            "tags": [
                "slope"
            ],
            "boundingBox": {
                "height": 22.285714285714285,
                "width": 20,
                "left": 182,
                "top": 410.85714285714283
            },
            "points": [
                {
                    "x": 182,
                    "y": 410.85714285714283
                },
                {
                    "x": 202,
                    "y": 410.85714285714283
                },
                {
                    "x": 202,
                    "y": 433.1428571428571
                },
                {
                    "x": 182,
                    "y": 433.1428571428571
                }
            ]
        },
        {
            "id": "eSc9EFRFZ",
            "type": "RECTANGLE",
            "tags": [
                "slope"
            ],
            "boundingBox": {
                "height": 38.285714285714285,
                "width": 43.42857142857142,
                "left": 70.57142857142857,
                "top": 448.57142857142856
            },
            "points": [
                {
                    "x": 70.57142857142857,
                    "y": 448.57142857142856
                },
                {
                    "x": 114,
                    "y": 448.57142857142856
                },
                {
                    "x": 114,
                    "y": 486.85714285714283
                },
                {
                    "x": 70.57142857142857,
                    "y": 486.85714285714283
                }
            ]
        }
    ],
    "version": "2.1.0"
}